PmedConnect/ParseFields.py
PmedConnect/ParseFunctions.py
PmedConnect/PubmedAPI.py
PmedConnect/ReadPMC.py
PmedConnect/__init__.py
PmedConnect/config.py
PmedConnect/tests/fetch_output.xml
PmedConnect/tests/search_output.xml
PmedConnect-0.1.4.dist-info/LICENSE
PmedConnect-0.1.4.dist-info/METADATA
PmedConnect-0.1.4.dist-info/WHEEL
PmedConnect-0.1.4.dist-info/top_level.txt
PmedConnect-0.1.4.dist-info/RECORD
