Metadata-Version: 2.1
Name: PmedConnect
Version: 0.1.4
Summary: Searches and fetches results from PubMed
Home-page: http://github.com/AMCeScience/PmedConnect
Author: Allard van Altena
Author-email: a.j.vanaltena@amc.uva.nl
License: GPL-3.0
Platform: UNKNOWN
License-File: LICENSE
Requires-Dist: progressbar2
Requires-Dist: Biopython
